pipeline_ui/__init__.py
pipeline_ui/modules/auth/auth.py
pipeline_ui/modules/auth/cli.py
pipeline_ui/modules/beam/utils.py
pipeline_ui/modules/cli/cli.py
pipeline_ui/modules/common/dependencies.py
pipeline_ui/modules/common_parser/code_validator.py
pipeline_ui/modules/common_parser/full_code_extractor.py
pipeline_ui/modules/common_parser/function_parser_extractor.py
pipeline_ui/modules/common_parser/import_merger.py
pipeline_ui/modules/common_parser/schema.py
pipeline_ui/modules/docs/router.py
pipeline_ui/modules/io_manager/io_manager.py
pipeline_ui/modules/node/decorator.py
pipeline_ui/modules/node/node.py
pipeline_ui/modules/node/node_manager.py
pipeline_ui/modules/node/router.py
pipeline_ui/modules/node/_instance/base_schema.py
pipeline_ui/modules/node/_instance/common_schema.py
pipeline_ui/modules/node/_instance/media_schema.py
pipeline_ui/modules/node/_instance/schema.py
pipeline_ui/modules/node/_instance/parameter/schema.py
pipeline_ui/modules/node/_parameter/base_schema.py
pipeline_ui/modules/node/_parameter/media_schema.py
pipeline_ui/modules/node/_parameter/schema.py
pipeline_ui/modules/node/_pin/base_schema.py
pipeline_ui/modules/node/_pin/media_schema.py
pipeline_ui/modules/node/parser/get_method_args.py
pipeline_ui/modules/node/parser/node_input_parser.py
pipeline_ui/modules/node/parser/node_output_parser.py
pipeline_ui/modules/node/parser/parameter_parser.py
pipeline_ui/modules/node/parser/stream.py
pipeline_ui/modules/node/schema/node_schema.py
pipeline_ui/modules/pack/cli.py
pipeline_ui/modules/pack/pack.py
pipeline_ui/modules/pack/default_files/.gitignore
pipeline_ui/modules/pack/default_files/.python-version
pipeline_ui/modules/pack/default_files/README.md
pipeline_ui/modules/pack/default_files/main.py
pipeline_ui/modules/pack/default_files/pyproject.toml
pipeline_ui/modules/pui/auto_loader.py
pipeline_ui/modules/pui/pui.py
pipeline_ui/modules/registry/cli.py
pipeline_ui/modules/registry/registry.py
pipeline_ui/modules/testing/testing_var.py
pipeline_ui-0.0.5.dist-info/METADATA
pipeline_ui-0.0.5.dist-info/WHEEL
pipeline_ui-0.0.5.dist-info/entry_points.txt
pipeline_ui-0.0.5.dist-info/RECORD
